ddoregio/Cluster.py
ddoregio/SCT.py
ddoregio/__init__.py
ddoregio/pyregiorust.py
ddoregio/regiotool.py
ddoregio/test.py
ddoregio-0.0.1.dist-info/LICENSE
ddoregio-0.0.1.dist-info/METADATA
ddoregio-0.0.1.dist-info/WHEEL
ddoregio-0.0.1.dist-info/top_level.txt
ddoregio-0.0.1.dist-info/RECORD
