Metadata-Version: 2.1
Name: ddoregio
Version: 0.0.1
Summary: A Branch-and-Bound Approach Using Decision Diagrams for Regionalization
Author-email: Nicolas Golenvaux <nicolas.golenvaux@uclouvain.be>
Project-URL: Homepage, https://github.com/pypa/sampleproject
Project-URL: Bug Tracker, https://github.com/pypa/sampleproject/issues
Classifier: Programming Language :: Python :: 3
Classifier: License :: OSI Approved :: MIT License
Classifier: Operating System :: OS Independent
Requires-Python: >=3.6
License-File: LICENSE
